Workbook

Sheet Sales Transactions
A1: TECHWARE SOLUTIONS PVT. LTD.
A2: Monthly Sales Report - January 2024
A3: Company: TechWare Solutions | Email: sales@techware.com | Phone: +91-11-4050-8888
A5: ID | B5: Date | C5: Product Name | D5: Quantity | E5: Unit Price | F5: Discount % | G5: Total Amount
A6: TW2024010001 | B6: 21-01-2024 | C6: Desktop Workstation | D6: 1 | E6: 120000 | F6: 10 | G6: =D6*E6*(1-F6/100) -> 108000
A7: TW2024010002 | B7: 08-01-2024 | C7: Keyboard Mechanical | D7: 3 | E7: 8500 | F7: 0 | G7: =D7*E7*(1-F7/100) -> 25500
A8: TW2024010003 | B8: 22-01-2024 | C8: Desktop Workstation | D8: 10 | E8: 120000 | F8: 15 | G8: =D8*E8*(1-F8/100) -> 1020000
A9: TW2024010004 | B9: 02-01-2024 | C9: Laptop Pro 15 | D9: 2 | E9: 85000 | F9: 5 | G9: =D9*E9*(1-F9/100) -> 161500
A10: TW2024010005 | B10: 08-01-2024 | C10: Laptop Pro 15 | D10: 9 | E10: 85000 | F10: 5 | G10: =D10*E10*(1-F10/100) -> 726750
A11: TW2024010006 | B11: 23-01-2024 | C11: External SSD 1TB | D11: 4 | E11: 12000 | F11: 15 | G11: =D11*E11*(1-F11/100) -> 40800
A12: TW2024010007 | B12: 19-01-2024 | C12: Mouse Wireless | D12: 13 | E12: 2500 | F12: 0 | G12: =D12*E12*(1-F12/100) -> 32500
A13: TW2024010008 | B13: 25-01-2024 | C13: Monitor 4K | D13: 12 | E13: 35000 | F13: 15 | G13: =D13*E13*(1-F13/100) -> 357000
A14: TW2024010009 | B14: 11-01-2024 | C14: Mouse Wireless | D14: 3 | E14: 2500 | F14: 5 | G14: =D14*E14*(1-F14/100) -> 7125
A15: TW2024010010 | B15: 31-01-2024 | C15: Webcam HD | D15: 2 | E15: 5000 | F15: 0 | G15: =D15*E15*(1-F15/100) -> 10000
A16: TW2024010011 | B16: 13-01-2024 | C16: Desktop Workstation | D16: 6 | E16: 120000 | F16: 10 | G16: =D16*E16*(1-F16/100) -> 648000
A17: TW2024010012 | B17: 20-01-2024 | C17: Mouse Wireless | D17: 13 | E17: 2500 | F17: 0 | G17: =D17*E17*(1-F17/100) -> 32500
... A25: TW2024010020 | B25: 12-01-2024 | C25: Keyboard Mechanical | D25: 11 | E25: 8500 | F25: 10 | G25: =D25*E25*(1-F25/100) -> 84150
A27: SUMMARY REPORT
A29: Total Transactions: | B29: =COUNTA(A6:A25) -> 20
A30: Total Revenue: | B30: =SUM(G6:G25) -> 4224675
A31: Total Units Sold: | B31: =SUM(D6:D25) -> 123
A32: Average Order Value: | B32: =AVERAGE(G6:G25) -> 211233.75
A33: Highest Sale: | B33: =MAX(G6:G25) -> 1020000
A34: Lowest Sale: | B34: =MIN(G6:G25) -> 4750

Sheet Product Analysis
A1: TECHWARE SOLUTIONS PVT. LTD.
A2: Product-wise Sales Analysis
A4: Product Name | B4: Units Sold | C4: Total Sales | D4: Percentage
A5: Laptop Pro 15 | B5: =SUMIF('Sales Transactions'!$C$6:$C$25,A5,'Sales Transactions'!$D$6:$D$25) -> 11 | C5: =SUMIF('Sales Transactions'!$C$6:$C$25,A5,'Sales Transactions'!$G$6:$G$25) -> 888250 | D5: =IF(SUM($C$5:$C$12)=0,0,C5/SUM($C$5:$C$12)) -> 0.21025286
A6: Desktop Workstation | B6: =SUMIF('Sales Transactions'!$C$6:$C$25,A6,'Sales Transactions'!$D$6:$D$25) -> 25 | C6: =SUMIF('Sales Transactions'!$C$6:$C$25,A6,'Sales Transactions'!$G$6:$G$25) -> 2646000 | D6: =IF(SUM($C$5:$C$12)=0,0,C6/SUM($C$5:$C$12)) -> 0.62632037
A7: Monitor 4K | B7: =SUMIF('Sales Transactions'!$C$6:$C$25,A7,'Sales Transactions'!$D$6:$D$25) -> 12 | C7: =SUMIF('Sales Transactions'!$C$6:$C$25,A7,'Sales Transactions'!$G$6:$G$25) -> 357000 | D7: =IF(SUM($C$5:$C$12)=0,0,C7/SUM($C$5:$C$12)) -> 0.084503542
A8: Keyboard Mechanical | B8: =SUMIF('Sales Transactions'!$C$6:$C$25,A8,'Sales Transactions'!$D$6:$D$25) -> 14 | C8: =SUMIF('Sales Transactions'!$C$6:$C$25,A8,'Sales Transactions'!$G$6:$G$25) -> 109650 | D8: =IF(SUM($C$5:$C$12)=0,0,C8/SUM($C$5:$C$12)) -> 0.025954659
A9: Mouse Wireless | B9: =SUMIF('Sales Transactions'!$C$6:$C$25,A9,'Sales Transactions'!$D$6:$D$25) -> 31 | C9: =SUMIF('Sales Transactions'!$C$6:$C$25,A9,'Sales Transactions'!$G$6:$G$25) -> 76875 | D9: =IF(SUM($C$5:$C$12)=0,0,C9/SUM($C$5:$C$12)) -> 0.018196666
A10: Webcam HD | B10: =SUMIF('Sales Transactions'!$C$6:$C$25,A10,'Sales Transactions'!$D$6:$D$25) -> 15 | C10: =SUMIF('Sales Transactions'!$C$6:$C$25,A10,'Sales Transactions'!$G$6:$G$25) -> 71000 | D10: =IF(SUM($C$5:$C$12)=0,0,C10/SUM($C$5:$C$12)) -> 0.016806026
A11: External SSD 1TB | B11: =SUMIF('Sales Transactions'!$C$6:$C$25,A11,'Sales Transactions'!$D$6:$D$25) -> 6 | C11: =SUMIF('Sales Transactions'!$C$6:$C$25,A11,'Sales Transactions'!$G$6:$G$25) -> 62400 | D11: =IF(SUM($C$5:$C$12)=0,0,C11/SUM($C$5:$C$12)) -> 0.014770367
A12: USB Hub | B12: =SUMIF('Sales Transactions'!$C$6:$C$25,A12,'Sales Transactions'!$D$6:$D$25) -> 9 | C12: =SUMIF('Sales Transactions'!$C$6:$C$25,A12,'Sales Transactions'!$G$6:$G$25) -> 13500 | D12: =IF(SUM($C$5:$C$12)=0,0,C12/SUM($C$5:$C$12)) -> 0.0031955121
A13: TOTAL | B13: =SUM(B5:B12) -> 123 | C13: =SUM(C5:C12) -> 4224675 | D13: =SUM(D5:D12) -> 1
